Metadata-Version: 2.1
Name: odoo13-addon-shopinvader-locomotive
Version: 13.0.3.1.1
Summary: Manage communications between Shopinvader and Locomotive CMS
Home-page: https://github.com/shopinvader/odoo-shopinvader
Author: Akretion
License: AGPL-3
Platform: UNKNOWN
Classifier: Programming Language :: Python
Classifier: Framework :: Odoo
Classifier: License :: OSI Approved :: GNU Affero General Public License v3
Classifier: Development Status :: 5 - Production/Stable
Requires-Python: >=3.5
Requires-Dist: locomotivecms
Requires-Dist: odoo13-addon-connector
Requires-Dist: odoo13-addon-queue-job
Requires-Dist: odoo13-addon-shopinvader
Requires-Dist: odoo13-addon-shopinvader-search-engine
Requires-Dist: odoo (<13.1dev,>=13.0a)
